LICENSE.txt
MANIFEST.in
README.rst
setup.py
src/chainreaction/__init__.py
src/chainreaction/reactor.py
src/chainreaction.egg-info/PKG-INFO
src/chainreaction.egg-info/SOURCES.txt
src/chainreaction.egg-info/dependency_links.txt
src/chainreaction.egg-info/top_level.txt
test/test_reactor.py
test/test_ref.py
test/utils.py